{
  "url": "https://dockets.justia.com/docket/new-york/nyedce/1:2026cv02629/545476",
  "title": "Squire v. JetBlue Airways Corporation 1:2026cv02629 | U.S. District Court for the Eastern District of New York | Justia",
  "industry": "aviation",
  "company": "jetblue",
  "page_name": "squire-v-jetblue-airways-corporation-1-2026cv02629",
  "source_type": "html",
  "saved_files": [
    "raw.html",
    "raw.txt"
  ],
  "date_scraped": "2026-05-07T17:13:49Z",
  "scraped_by": "",
  "notes": "Generated from local saved HTML file: Squire v. JetBlue Airways Corporation 1:2026cv02629 | U.S. District Court for the Eastern District o.html. Case filed 2026-05-01 according to page metadata.",
  "tags": [
    "lawsuit",
    "class action",
    "JetBlue Airways Corporation",
    "wiretapping",
    "Justia docket",
    "Eastern District of New York"
  ],
  "language": "en",
  "access_date": "2026-05-07",
  "status": "complete"
}
